{
  "version" : 1,
  "numFrames" : 15,
  "numBones" : 21,
  "rotationOrder1" : 1,
  "rotationOrder2" : 0,
  "rotationOrder3" : 2,
  "animationFrames" : [ {
    "rootRotation" : {
      "x" : 0.0,
      "y" : 359.82422,
      "z" : 0.0
    },
    "rootTranslation" : {
      "x" : -2.3548408E-4,
      "y" : 13.528447,
      "z" : 0.12610927
    },
    "boneRotations" : [ {
      "x" : 281.07422,
      "y" : 240.0293,
      "z" : 269.9121
    }, {
      "x" : 355.07812,
      "y" : 346.0254,
      "z" : 359.82422
    }, {
      "x" : 7.998047,
      "y" : 359.82422,
      "z" : 304.10156
    }, {
      "x" : 353.23242,
      "y" : 311.04492,
      "z" : 75.234375
    }, {
      "x" : 309.11133,
      "y" : 334.42383,
      "z" : 30.585938
    }, {
      "x" : 33.75,
      "y" : 352.79297,
      "z" : 77.16797
    }, {
      "x" : 357.89062,
      "y" : 321.85547,
      "z" : 1.6699219
    }, {
      "x" : 0.0,
      "y" : 30.058594,
      "z" : 0.0
    }, {
      "x" : 353.4082,
      "y" : 20.917969,
      "z" : 284.50195
    }, {
      "x" : 308.05664,
      "y" : 22.58789,
      "z" : 331.69922
    }, {
      "x" : 36.73828,
      "y" : 3.1640625,
      "z" : 275.18555
    }, {
      "x" : 1.5820312,
      "y" : 30.410156,
      "z" : 0.9667969
    }, {
      "x" : 0.0,
      "y" : 336.26953,
      "z" : 0.0
    }, {
      "x" : 0.0,
      "y" : 41.660156,
      "z" : 180.0
    }, {
      "x" : 284.67773,
      "y" : 282.91992,
      "z" : 122.87109
    }, {
      "x" : 12.744141,
      "y" : 3.9550781,
      "z" : 25.664062
    }, {
      "x" : 286.61133,
      "y" : 307.96875,
      "z" : 55.371094
    }, {
      "x" : 0.0,
      "y" : 260.15625,
      "z" : 180.0
    }, {
      "x" : 280.2832,
      "y" : 343.91602,
      "z" : 309.4629
    }, {
      "x" : 1.40625,
      "y" : 354.4629,
      "z" : 359.82422
    }, {
      "x" : 346.28906,
      "y" : 78.22266,
      "z" : 270.0
    } ]
  }, {
    "rootRotation" : {
      "x" : 0.0,
      "y" : 359.38477,
      "z" : 0.0
    },
    "rootTranslation" : {
      "x" : -7.970101E-4,
      "y" : 13.512143,
      "z" : 0.39477968
    },
    "boneRotations" : [ {
      "x" : 279.14062,
      "y" : 234.66797,
      "z" : 269.9121
    }, {
      "x" : 356.48438,
      "y" : 349.27734,
      "z" : 9.755859
    }, {
      "x" : 7.998047,
      "y" : 359.82422,
      "z" : 314.64844
    }, {
      "x" : 0.0,
      "y" : 314.64844,
      "z" : 82.5293
    }, {
      "x" : 309.11133,
      "y" : 334.42383,
      "z" : 30.585938
    }, {
      "x" : 32.34375,
      "y" : 352.6172,
      "z" : 76.28906
    }, {
      "x" : 354.90234,
      "y" : 322.99805,
      "z" : 3.8671875
    }, {
      "x" : 0.0,
      "y" : 24.521484,
      "z" : 0.0
    }, {
      "x" : 348.92578,
      "y" : 23.554688,
      "z" : 293.5547
    }, {
      "x" : 306.38672,
      "y" : 17.138672,
      "z" : 336.00586
    }, {
      "x" : 35.859375,
      "y" : 4.3066406,
      "z" : 277.29492
    }, {
      "x" : 357.80273,
      "y" : 32.43164,
      "z" : 358.59375
    }, {
      "x" : 0.0,
      "y" : 340.75195,
      "z" : 0.0
    }, {
      "x" : 0.0,
      "y" : 36.5625,
      "z" : 180.0
    }, {
      "x" : 286.875,
      "y" : 288.28125,
      "z" : 120.146484
    }, {
      "x" : 17.050781,
      "y" : 4.921875,
      "z" : 21.00586
    }, {
      "x" : 284.67773,
      "y" : 297.42188,
      "z" : 67.58789
    }, {
      "x" : 0.0,
      "y" : 254.9707,
      "z" : 180.0
    }, {
      "x" : 281.68945,
      "y" : 339.60938,
      "z" : 309.19922
    }, {
      "x" : 1.1425781,
      "y" : 351.73828,
      "z" : 359.73633
    }, {
      "x" : 341.98242,
      "y" : 80.24414,
      "z" : 269.1211
    } ]
  }, {
    "rootRotation" : {
      "x" : 0.0,
      "y" : 358.9453,
      "z" : 0.0
    },
    "rootTranslation" : {
      "x" : -0.0014671605,
      "y" : 13.492684,
      "z" : 0.6741551
    },
    "boneRotations" : [ {
      "x" : 277.11914,
      "y" : 229.57031,
      "z" : 269.9121
    }, {
      "x" : 356.83594,
      "y" : 352.6172,
      "z" : 20.214844
    }, {
      "x" : 7.998047,
      "y" : 359.82422,
      "z" : 325.45898
    }, {
      "x" : 6.2402344,
      "y" : 319.04297,
      "z" : 91.05469
    }, {
      "x" : 309.11133,
      "y" : 334.42383,
      "z" : 30.585938
    }, {
      "x" : 31.02539,
      "y" : 352.26562,
      "z" : 75.234375
    }, {
      "x" : 351.73828,
      "y" : 323.70117,
      "z" : 6.064453
    }, {
      "x" : 0.0,
      "y" : 18.808594,
      "z" : 0.0
    }, {
      "x" : 343.47656,
      "y" : 25.3125,
      "z" : 302.7832
    }, {
      "x" : 304.98047,
      "y" : 11.074219,
      "z" : 341.01562
    }, {
      "x" : 35.15625,
      "y" : 5.5371094,
      "z" : 279.58008
    }, {
      "x" : 354.11133,
      "y" : 34.98047,
      "z" : 355.86914
    }, {
      "x" : 0.0,
      "y" : 345.41016,
      "z" : 0.0
    }, {
      "x" : 0.0,
      "y" : 31.640625,
      "z" : 180.0
    }, {
      "x" : 289.24805,
      "y" : 293.20312,
      "z" : 117.77344
    }, {
      "x" : 21.533203,
      "y" : 5.185547,
      "z" : 16.259766
    }, {
      "x" : 283.62305,
      "y" : 283.44727,
      "z" : 83.32031
    }, {
      "x" : 0.0,
      "y" : 249.96094,
      "z" : 180.0
    }, {
      "x" : 283.1836,
      "y" : 335.21484,
      "z" : 309.02344
    }, {
      "x" : 0.87890625,
      "y" : 348.92578,
      "z" : 359.73633
    }, {
      "x" : 337.76367,
      "y" : 82.44141,
      "z" : 268.1543
    } ]
  }, {
    "rootRotation" : {
      "x" : 0.0,
      "y" : 358.50586,
      "z" : 0.0
    },
    "rootTranslation" : {
      "x" : -0.0020285547,
      "y" : 13.47638,
      "z" : 0.94281656
    },
    "boneRotations" : [ {
      "x" : 275.18555,
      "y" : 224.29688,
      "z" : 269.9121
    }, {
      "x" : 356.2207,
      "y" : 355.60547,
      "z" : 30.410156
    }, {
      "x" : 7.998047,
      "y" : 359.73633,
      "z" : 336.00586
    }, {
      "x" : 11.162109,
      "y" : 323.96484,
      "z" : 99.93164
    }, {
      "x" : 309.11133,
      "y" : 334.42383,
      "z" : 30.585938
    }, {
      "x" : 29.61914,
      "y" : 352.17773,
      "z" : 74.44336
    }, {
      "x" : 348.6621,
      "y" : 324.4922,
      "z" : 7.998047
    }, {
      "x" : 0.0,
      "y" : 13.271484,
      "z" : 0.0
    }, {
      "x" : 337.67578,
      "y" : 25.927734,
      "z" : 311.57227
    }, {
      "x" : 304.01367,
      "y" : 4.8339844,
      "z" : 346.11328
    }, {
      "x" : 34.189453,
      "y" : 6.591797,
      "z" : 281.51367
    }, {
      "x" : 350.6836,
      "y" : 37.265625,
      "z" : 352.96875
    }, {
      "x" : 0.0,
      "y" : 349.89258,
      "z" : 0.0
    }, {
      "x" : 0.0,
      "y" : 26.542969,
      "z" : 180.0
    }, {
      "x" : 291.4453,
      "y" : 297.42188,
      "z" : 116.103516
    }, {
      "x" : 26.103516,
      "y" : 4.658203,
      "z" : 11.513672
    }, {
      "x" : 283.53516,
      "y" : 268.59375,
      "z" : 99.75586
    }, {
      "x" : 0.0,
      "y" : 244.77539,
      "z" : 180.0
    }, {
      "x" : 284.58984,
      "y" : 330.8203,
      "z" : 308.93555
    }, {
      "x" : 0.6152344,
      "y" : 346.20117,
      "z" : 359.82422
    }, {
      "x" : 333.54492,
      "y" : 84.63867,
      "z" : 267.1875
    } ]
  }, {
    "rootRotation" : {
      "x" : 0.0,
      "y" : 358.33008,
      "z" : 0.0
    },
    "rootTranslation" : {
      "x" : -0.0022639476,
      "y" : 13.469543,
      "z" : 1.1793509
    },
    "boneRotations" : [ {
      "x" : 273.33984,
      "y" : 218.58398,
      "z" : 269.82422
    }, {
      "x" : 354.99023,
      "y" : 357.80273,
      "z" : 39.375
    }, {
      "x" : 8.0859375,
      "y" : 359.73633,
      "z" : 345.49805
    }, {
      "x" : 14.589844,
      "y" : 328.79883,
      "z" : 108.54492
    }, {
      "x" : 309.11133,
      "y" : 334.42383,
      "z" : 30.585938
    }, {
      "x" : 27.685547,
      "y" : 352.5293,
      "z" : 74.26758
    }, {
      "x" : 345.67383,
      "y" : 326.1621,
      "z" : 9.404297
    }, {
      "x" : 0.0,
      "y" : 8.261719,
      "z" : 0.0
    }, {
      "x" : 332.22656,
      "y" : 25.488281,
      "z" : 319.5703
    }, {
      "x" : 303.31055,
      "y" : 359.1211,
      "z" : 350.85938
    }, {
      "x" : 32.695312,
      "y" : 7.03125,
      "z" : 282.91992
    }, {
      "x" : 347.6953,
      "y" : 38.408203,
      "z" : 350.41992
    }, {
      "x" : 0.0,
      "y" : 353.84766,
      "z" : 0.0
    }, {
      "x" : 0.0,
      "y" : 20.742188,
      "z" : 180.0
    }, {
      "x" : 293.3789,
      "y" : 300.58594,
      "z" : 115.48828
    }, {
      "x" : 30.322266,
      "y" : 3.515625,
      "z" : 7.1191406
    }, {
      "x" : 284.23828,
      "y" : 256.11328,
      "z" : 113.64258
    }, {
      "x" : 0.0,
      "y" : 238.88672,
      "z" : 180.0
    }, {
      "x" : 285.9082,
      "y" : 326.68945,
      "z" : 309.02344
    }, {
      "x" : 0.3515625,
      "y" : 343.82812,
      "z" : 359.82422
    }, {
      "x" : 329.1504,
      "y" : 86.92383,
      "z" : 266.2207
    } ]
  }, {
    "rootRotation" : {
      "x" : 0.0,
      "y" : 358.50586,
      "z" : 0.0
    },
    "rootTranslation" : {
      "x" : -0.0019561225,
      "y" : 13.478484,
      "z" : 1.3623445
    },
    "boneRotations" : [ {
      "x" : 271.7578,
      "y" : 212.16797,
      "z" : 269.64844
    }, {
      "x" : 353.4961,
      "y" : 359.20898,
      "z" : 46.31836
    }, {
      "x" : 8.0859375,
      "y" : 359.82422,
      "z" : 353.23242
    }, {
      "x" : 16.523438,
      "y" : 332.8418,
      "z" : 115.66406
    }, {
      "x" : 309.11133,
      "y" : 334.42383,
      "z" : 30.585938
    }, {
      "x" : 24.785156,
      "y" : 353.67188,
      "z" : 75.234375
    }, {
      "x" : 343.0371,
      "y" : 329.23828,
      "z" : 9.84375
    }, {
      "x" : 0.0,
      "y" : 4.0429688,
      "z" : 0.0
    }, {
      "x" : 327.74414,
      "y" : 24.257812,
      "z" : 325.98633
    }, {
      "x" : 303.04688,
      "y" : 354.63867,
      "z" : 354.63867
    }, {
      "x" : 30.146484,
      "y" : 6.6796875,
      "z" : 283.1836
    }, {
      "x" : 345.0586,
      "y" : 37.441406,
      "z" : 348.8379
    }, {
      "x" : 0.0,
      "y" : 357.1875,
      "z" : 0.0
    }, {
      "x" : 0.0,
      "y" : 13.798828,
      "z" : 180.0
    }, {
      "x" : 294.78516,
      "y" : 302.6953,
      "z" : 116.015625
    }, {
      "x" : 33.92578,
      "y" : 1.9335938,
      "z" : 3.3398438
    }, {
      "x" : 285.1172,
      "y" : 247.14844,
      "z" : 123.57422
    }, {
      "x" : 0.0,
      "y" : 231.94336,
      "z" : 180.0
    }, {
      "x" : 286.875,
      "y" : 322.99805,
      "z" : 309.2871
    }, {
      "x" : 0.17578125,
      "y" : 341.89453,
      "z" : 359.9121
    }, {
      "x" : 324.4922,
      "y" : 89.12109,
      "z" : 265.3418
    } ]
  }, {
    "rootRotation" : {
      "x" : 0.0,
      "y" : 359.29688,
      "z" : 0.0
    },
    "rootTranslation" : {
      "x" : -8.8757486E-4,
      "y" : 13.509514,
      "z" : 1.4703716
    },
    "boneRotations" : [ {
      "x" : 270.52734,
      "y" : 205.3125,
      "z" : 268.76953
    }, {
      "x" : 352.35352,
      "y" : 359.82422,
      "z" : 50.625
    }, {
      "x" : 8.0859375,
      "y" : 359.9121,
      "z" : 358.50586
    }, {
      "x" : 17.226562,
      "y" : 335.30273,
      "z" : 120.146484
    }, {
      "x" : 309.11133,
      "y" : 334.42383,
      "z" : 30.585938
    }, {
      "x" : 20.566406,
      "y" : 355.51758,
      "z" : 77.51953
    }, {
      "x" : 340.92773,
      "y" : 334.51172,
      "z" : 8.876953
    }, {
      "x" : 0.0,
      "y" : 0.9667969,
      "z" : 0.0
    }, {
      "x" : 324.93164,
      "y" : 23.291016,
      "z" : 330.0293
    }, {
      "x" : 302.8711,
      "y" : 352.00195,
      "z" : 356.83594
    }, {
      "x" : 26.191406,
      "y" : 5.4492188,
      "z" : 282.2168
    }, {
      "x" : 342.68555,
      "y" : 33.310547,
      "z" : 348.92578
    }, {
      "x" : 0.0,
      "y" : 359.38477,
      "z" : 0.0
    }, {
      "x" : 0.0,
      "y" : 5.361328,
      "z" : 180.0
    }, {
      "x" : 295.4004,
      "y" : 303.39844,
      "z" : 117.86133
    }, {
      "x" : 36.47461,
      "y" : 0.43945312,
      "z" : 0.703125
    }, {
      "x" : 285.46875,
      "y" : 241.34766,
      "z" : 129.81445
    }, {
      "x" : 0.0,
      "y" : 223.41797,
      "z" : 180.0
    }, {
      "x" : 287.57812,
      "y" : 320.09766,
      "z" : 309.81445
    }, {
      "x" : 0.0,
      "y" : 340.75195,
      "z" : 359.9121
    }, {
      "x" : 319.5703,
      "y" : 91.05469,
      "z" : 264.72656
    } ]
  }, {
    "rootRotation" : {
      "x" : 0.0,
      "y" : 0.87890625,
      "z" : 0.0
    },
    "rootTranslation" : {
      "x" : 0.0011502091,
      "y" : 13.568681,
      "z" : 1.4828682
    },
    "boneRotations" : [ {
      "x" : 270.35156,
      "y" : 13.535156,
      "z" : 91.40625
    }, {
      "x" : 351.73828,
      "y" : 0.0,
      "z" : 51.328125
    }, {
      "x" : 7.998047,
      "y" : 0.087890625,
      "z" : 0.6152344
    }, {
      "x" : 17.050781,
      "y" : 335.83008,
      "z" : 121.02539
    }, {
      "x" : 309.11133,
      "y" : 334.42383,
      "z" : 30.585938
    }, {
      "x" : 14.501953,
      "y" : 357.80273,
      "z" : 81.29883
    }, {
      "x" : 339.96094,
      "y" : 342.59766,
      "z" : 6.1523438
    }, {
      "x" : 0.0,
      "y" : 359.38477,
      "z" : 0.0
    }, {
      "x" : 324.14062,
      "y" : 23.203125,
      "z" : 330.46875
    }, {
      "x" : 302.8711,
      "y" : 351.91406,
      "z" : 356.92383
    }, {
      "x" : 20.478516,
      "y" : 3.4277344,
      "z" : 279.84375
    }, {
      "x" : 340.92773,
      "y" : 24.873047,
      "z" : 351.38672
    }, {
      "x" : 0.0,
      "y" : 0.26367188,
      "z" : 0.0
    }, {
      "x" : 0.0,
      "y" : 354.99023,
      "z" : 180.0
    }, {
      "x" : 295.04883,
      "y" : 302.25586,
      "z" : 121.552734
    }, {
      "x" : 37.96875,
      "y" : 359.64844,
      "z" : 359.64844
    }, {
      "x" : 284.9414,
      "y" : 238.1836,
      "z" : 132.71484
    }, {
      "x" : 0.0,
      "y" : 212.95898,
      "z" : 180.0
    }, {
      "x" : 287.8418,
      "y" : 317.98828,
      "z" : 310.60547
    }, {
      "x" : 359.9121,
      "y" : 340.48828,
      "z" : 359.9121
    }, {
      "x" : 314.20898,
      "y" : 92.46094,
      "z" : 264.375
    } ]
  }, {
    "rootRotation" : {
      "x" : 0.0,
      "y" : 3.0761719,
      "z" : 0.0
    },
    "rootTranslation" : {
      "x" : 0.0041551907,
      "y" : 13.655984,
      "z" : 1.3997573
    },
    "boneRotations" : [ {
      "x" : 270.79102,
      "y" : 3.7792969,
      "z" : 90.615234
    }, {
      "x" : 351.82617,
      "y" : 359.73633,
      "z" : 48.427734
    }, {
      "x" : 7.998047,
      "y" : 0.3515625,
      "z" : 359.64844
    }, {
      "x" : 15.908203,
      "y" : 334.42383,
      "z" : 118.38867
    }, {
      "x" : 309.11133,
      "y" : 334.42383,
      "z" : 30.585938
    }, {
      "x" : 6.4160156,
      "y" : 359.56055,
      "z" : 86.30859
    }, {
      "x" : 340.48828,
      "y" : 353.3203,
      "z" : 2.2851562
    }, {
      "x" : 0.0,
      "y" : 359.29688,
      "z" : 0.0
    }, {
      "x" : 325.3711,
      "y" : 24.345703,
      "z" : 327.39258
    }, {
      "x" : 302.95898,
      "y" : 354.19922,
      "z" : 354.99023
    }, {
      "x" : 12.65625,
      "y" : 1.40625,
      "z" : 276.32812
    }, {
      "x" : 340.66406,
      "y" : 12.128906,
      "z" : 355.95703
    }, {
      "x" : 0.0,
      "y" : 359.82422,
      "z" : 0.0
    }, {
      "x" : 0.0,
      "y" : 342.59766,
      "z" : 180.0
    }, {
      "x" : 294.08203,
      "y" : 298.65234,
      "z" : 127.44141
    }, {
      "x" : 38.320312,
      "y" : 359.64844,
      "z" : 0.3515625
    }, {
      "x" : 283.27148,
      "y" : 237.48047,
      "z" : 132.45117
    }, {
      "x" : 0.0,
      "y" : 200.47852,
      "z" : 180.0
    }, {
      "x" : 287.57812,
      "y" : 316.7578,
      "z" : 311.74805
    }, {
      "x" : 359.9121,
      "y" : 341.1914,
      "z" : 0.0
    }, {
      "x" : 308.4082,
      "y" : 93.33984,
      "z" : 264.55078
    } ]
  }, {
    "rootRotation" : {
      "x" : 0.0,
      "y" : 5.888672,
      "z" : 0.0
    },
    "rootTranslation" : {
      "x" : 0.007910999,
      "y" : 13.765377,
      "z" : 1.241477
    },
    "boneRotations" : [ {
      "x" : 270.9668,
      "y" : 352.17773,
      "z" : 90.43945
    }, {
      "x" : 352.35352,
      "y" : 359.1211,
      "z" : 42.890625
    }, {
      "x" : 7.998047,
      "y" : 0.703125,
      "z" : 356.2207
    }, {
      "x" : 13.886719,
      "y" : 331.61133,
      "z" : 113.02734
    }, {
      "x" : 309.11133,
      "y" : 334.42383,
      "z" : 30.585938
    }, {
      "x" : 356.74805,
      "y" : 359.82422,
      "z" : 92.37305
    }, {
      "x" : 342.86133,
      "y" : 5.888672,
      "z" : 358.2422
    }, {
      "x" : 0.0,
      "y" : 0.3515625,
      "z" : 0.0
    }, {
      "x" : 328.27148,
      "y" : 26.015625,
      "z" : 321.76758
    }, {
      "x" : 303.31055,
      "y" : 358.41797,
      "z" : 351.38672
    }, {
      "x" : 3.2519531,
      "y" : 0.087890625,
      "z" : 272.10938
    }, {
      "x" : 342.59766,
      "y" : 356.3086,
      "z" : 1.0546875
    }, {
      "x" : 0.0,
      "y" : 358.2422,
      "z" : 0.0
    }, {
      "x" : 0.0,
      "y" : 328.62305,
      "z" : 180.0
    }, {
      "x" : 292.76367,
      "y" : 292.4121,
      "z" : 135.8789
    }, {
      "x" : 37.88086,
      "y" : 0.3515625,
      "z" : 2.5488281
    }, {
      "x" : 280.72266,
      "y" : 239.76562,
      "z" : 128.75977
    }, {
      "x" : 0.0,
      "y" : 186.5039,
      "z" : 180.0
    }, {
      "x" : 287.05078,
      "y" : 316.0547,
      "z" : 313.2422
    }, {
      "x" : 359.82422,
      "y" : 342.50977,
      "z" : 0.0
    }, {
      "x" : 302.25586,
      "y" : 93.515625,
      "z" : 265.16602
    } ]
  }, {
    "rootRotation" : {
      "x" : 0.0,
      "y" : 9.140625,
      "z" : 0.0
    },
    "rootTranslation" : {
      "x" : 0.012184789,
      "y" : 13.890547,
      "z" : 1.029374
    },
    "boneRotations" : [ {
      "x" : 270.8789,
      "y" : 339.69727,
      "z" : 90.43945
    }, {
      "x" : 352.96875,
      "y" : 357.97852,
      "z" : 35.33203
    }, {
      "x" : 7.998047,
      "y" : 1.0546875,
      "z" : 351.03516
    }, {
      "x" : 10.8984375,
      "y" : 328.0078,
      "z" : 105.99609
    }, {
      "x" : 309.11133,
      "y" : 334.42383,
      "z" : 30.585938
    }, {
      "x" : 346.11328,
      "y" : 357.71484,
      "z" : 99.49219
    }, {
      "x" : 346.64062,
      "y" : 19.423828,
      "z" : 355.3418
    }, {
      "x" : 0.0,
      "y" : 2.2851562,
      "z" : 0.0
    }, {
      "x" : 332.40234,
      "y" : 27.597656,
      "z" : 314.47266
    }, {
      "x" : 303.8379,
      "y" : 3.9550781,
      "z" : 346.9043
    }, {
      "x" : 352.6172,
      "y" : 0.3515625,
      "z" : 267.2754
    }, {
      "x" : 346.64062,
      "y" : 338.81836,
      "z" : 5.0976562
    }, {
      "x" : 0.0,
      "y" : 355.95703,
      "z" : 0.0
    }, {
      "x" : 0.0,
      "y" : 313.50586,
      "z" : 180.0
    }, {
      "x" : 291.79688,
      "y" : 283.62305,
      "z" : 146.68945
    }, {
      "x" : 36.82617,
      "y" : 1.40625,
      "z" : 5.625
    }, {
      "x" : 277.73438,
      "y" : 247.93945,
      "z" : 118.828125
    }, {
      "x" : 0.0,
      "y" : 171.47461,
      "z" : 180.0
    }, {
      "x" : 286.25977,
      "y" : 315.70312,
      "z" : 315.17578
    }, {
      "x" : 359.9121,
      "y" : 344.44336,
      "z" : 0.0
    }, {
      "x" : 295.83984,
      "y" : 92.8125,
      "z" : 266.39648
    } ]
  }, {
    "rootRotation" : {
      "x" : 0.0,
      "y" : 12.568359,
      "z" : 0.0
    },
    "rootTranslation" : {
      "x" : 0.016738884,
      "y" : 14.025184,
      "z" : 0.7848294
    },
    "boneRotations" : [ {
      "x" : 270.61523,
      "y" : 326.60156,
      "z" : 90.43945
    }, {
      "x" : 353.4082,
      "y" : 356.57227,
      "z" : 26.63086
    }, {
      "x" : 8.173828,
      "y" : 1.4941406,
      "z" : 344.79492
    }, {
      "x" : 6.767578,
      "y" : 324.3164,
      "z" : 98.26172
    }, {
      "x" : 309.11133,
      "y" : 334.42383,
      "z" : 30.585938
    }, {
      "x" : 335.6543,
      "y" : 352.26562,
      "z" : 108.28125
    }, {
      "x" : 351.21094,
      "y" : 33.398438,
      "z" : 354.19922
    }, {
      "x" : 0.0,
      "y" : 4.658203,
      "z" : 0.0
    }, {
      "x" : 337.14844,
      "y" : 28.476562,
      "z" : 306.5625
    }, {
      "x" : 304.8047,
      "y" : 9.931641,
      "z" : 341.89453
    }, {
      "x" : 341.54297,
      "y" : 2.6367188,
      "z" : 261.6504
    }, {
      "x" : 351.73828,
      "y" : 320.625,
      "z" : 6.6796875
    }, {
      "x" : 0.0,
      "y" : 353.23242,
      "z" : 0.0
    }, {
      "x" : 0.0,
      "y" : 297.77344,
      "z" : 180.0
    }, {
      "x" : 291.5332,
      "y" : 273.07617,
      "z" : 159.08203
    }, {
      "x" : 35.33203,
      "y" : 2.5488281,
      "z" : 9.316406
    }, {
      "x" : 275.09766,
      "y" : 271.58203,
      "z" : 93.427734
    }, {
      "x" : 0.0,
      "y" : 155.74219,
      "z" : 180.0
    }, {
      "x" : 285.29297,
      "y" : 315.26367,
      "z" : 317.46094
    }, {
      "x" : 359.9121,
      "y" : 346.64062,
      "z" : 359.9121
    }, {
      "x" : 289.33594,
      "y" : 90.9668,
      "z" : 268.59375
    } ]
  }, {
    "rootRotation" : {
      "x" : 0.0,
      "y" : 16.083984,
      "z" : 0.0
    },
    "rootTranslation" : {
      "x" : 0.021336855,
      "y" : 14.162976,
      "z" : 0.5292714
    },
    "boneRotations" : [ {
      "x" : 270.35156,
      "y" : 313.2422,
      "z" : 90.615234
    }, {
      "x" : 353.4082,
      "y" : 354.81445,
      "z" : 17.490234
    }, {
      "x" : 8.4375,
      "y" : 1.8457031,
      "z" : 338.20312
    }, {
      "x" : 1.8457031,
      "y" : 320.97656,
      "z" : 90.703125
    }, {
      "x" : 309.11133,
      "y" : 334.42383,
      "z" : 30.585938
    }, {
      "x" : 326.60156,
      "y" : 342.86133,
      "z" : 119.35547
    }, {
      "x" : 355.4297,
      "y" : 47.460938,
      "z" : 354.99023
    }, {
      "x" : 0.0,
      "y" : 7.2070312,
      "z" : 0.0
    }, {
      "x" : 342.0703,
      "y" : 28.564453,
      "z" : 298.47656
    }, {
      "x" : 306.12305,
      "y" : 15.908203,
      "z" : 337.06055
    }, {
      "x" : 330.73242,
      "y" : 7.5585938,
      "z" : 254.79492
    }, {
      "x" : 356.39648,
      "y" : 302.16797,
      "z" : 5.7128906
    }, {
      "x" : 0.0,
      "y" : 350.41992,
      "z" : 0.0
    }, {
      "x" : 0.0,
      "y" : 281.86523,
      "z" : 180.0
    }, {
      "x" : 292.4121,
      "y" : 262.4414,
      "z" : 171.38672
    }, {
      "x" : 33.83789,
      "y" : 3.515625,
      "z" : 13.0078125
    }, {
      "x" : 274.6582,
      "y" : 317.63672,
      "z" : 45.527344
    }, {
      "x" : 0.0,
      "y" : 139.7461,
      "z" : 180.0
    }, {
      "x" : 284.41406,
      "y" : 314.64844,
      "z" : 320.18555
    }, {
      "x" : 359.9121,
      "y" : 348.92578,
      "z" : 359.9121
    }, {
      "x" : 282.83203,
      "y" : 86.572266,
      "z" : 273.25195
    } ]
  }, {
    "rootRotation" : {
      "x" : 0.0,
      "y" : 19.511719,
      "z" : 0.0
    },
    "rootTranslation" : {
      "x" : 0.025751531,
      "y" : 14.297613,
      "z" : 0.2841802
    },
    "boneRotations" : [ {
      "x" : 270.0879,
      "y" : 299.44336,
      "z" : 91.40625
    }, {
      "x" : 352.88086,
      "y" : 353.14453,
      "z" : 8.876953
    }, {
      "x" : 8.701172,
      "y" : 2.1972656,
      "z" : 331.9629
    }, {
      "x" : 356.57227,
      "y" : 318.33984,
      "z" : 83.84766
    }, {
      "x" : 309.11133,
      "y" : 334.42383,
      "z" : 30.585938
    }, {
      "x" : 320.36133,
      "y" : 329.41406,
      "z" : 132.80273
    }, {
      "x" : 358.50586,
      "y" : 61.435547,
      "z" : 357.2754
    }, {
      "x" : 0.0,
      "y" : 9.580078,
      "z" : 0.0
    }, {
      "x" : 346.46484,
      "y" : 27.949219,
      "z" : 290.7422
    }, {
      "x" : 307.6172,
      "y" : 21.18164,
      "z" : 332.7539
    }, {
      "x" : 321.15234,
      "y" : 15.556641,
      "z" : 246.00586
    }, {
      "x" : 359.20898,
      "y" : 284.0625,
      "z" : 3.0761719
    }, {
      "x" : 0.0,
      "y" : 347.60742,
      "z" : 0.0
    }, {
      "x" : 0.0,
      "y" : 266.1328,
      "z" : 180.0
    }, {
      "x" : 294.16992,
      "y" : 253.56445,
      "z" : 181.75781
    }, {
      "x" : 32.43164,
      "y" : 4.21875,
      "z" : 16.523438
    }, {
      "x" : 276.85547,
      "y" : 347.8711,
      "z" : 13.535156
    }, {
      "x" : 0.0,
      "y" : 124.01367,
      "z" : 180.0
    }, {
      "x" : 283.53516,
      "y" : 313.59375,
      "z" : 323.17383
    }, {
      "x" : 0.0,
      "y" : 351.12305,
      "z" : 359.9121
    }, {
      "x" : 276.5918,
      "y" : 73.65234,
      "z" : 286.25977
    } ]
  }, {
    "rootRotation" : {
      "x" : 0.0,
      "y" : 22.763672,
      "z" : 0.0
    },
    "rootTranslation" : {
      "x" : 0.029772522,
      "y" : 14.422784,
      "z" : 0.071086116
    },
    "boneRotations" : [ {
      "x" : 270.0,
      "y" : 18.36914,
      "z" : 0.0
    }, {
      "x" : 352.08984,
      "y" : 351.73828,
      "z" : 1.40625
    }, {
      "x" : 9.052734,
      "y" : 2.4609375,
      "z" : 326.77734
    }, {
      "x" : 351.6504,
      "y" : 316.58203,
      "z" : 78.22266
    }, {
      "x" : 309.11133,
      "y" : 334.42383,
      "z" : 30.585938
    }, {
      "x" : 317.63672,
      "y" : 313.76953,
      "z" : 147.1289
    }, {
      "x" : 0.0,
      "y" : 74.61914,
      "z" : 0.0
    }, {
      "x" : 0.0,
      "y" : 11.513672,
      "z" : 0.0
    }, {
      "x" : 350.06836,
      "y" : 26.894531,
      "z" : 284.0625
    }, {
      "x" : 309.11133,
      "y" : 25.576172,
      "z" : 329.41406
    }, {
      "x" : 313.59375,
      "y" : 26.80664,
      "z" : 235.10742
    }, {
      "x" : 0.0,
      "y" : 267.01172,
      "z" : 0.0
    }, {
      "x" : 0.0,
      "y" : 345.41016,
      "z" : 0.0
    }, {
      "x" : 0.0,
      "y" : 251.10352,
      "z" : 180.0
    }, {
      "x" : 296.54297,
      "y" : 247.23633,
      "z" : 189.58008
    }, {
      "x" : 31.464844,
      "y" : 4.658203,
      "z" : 19.511719
    }, {
      "x" : 279.58008,
      "y" : 0.0,
      "z" : 0.0
    }, {
      "x" : 0.0,
      "y" : 108.896484,
      "z" : 180.0
    }, {
      "x" : 282.83203,
      "y" : 312.0996,
      "z" : 326.1621
    }, {
      "x" : 0.0,
      "y" : 352.96875,
      "z" : 359.9121
    }, {
      "x" : 272.8125,
      "y" : 0.0,
      "z" : 0.0
    } ]
  } ]
}